tensorrtserver-1.11.0.data/purelib/tensorrtserver/__init__.py
tensorrtserver-1.11.0.data/purelib/tensorrtserver/api/__init__.py
tensorrtserver-1.11.0.data/purelib/tensorrtserver/api/api_pb2.py
tensorrtserver-1.11.0.data/purelib/tensorrtserver/api/grpc_service_pb2.py
tensorrtserver-1.11.0.data/purelib/tensorrtserver/api/grpc_service_pb2_grpc.py
tensorrtserver-1.11.0.data/purelib/tensorrtserver/api/libcrequest.so
tensorrtserver-1.11.0.data/purelib/tensorrtserver/api/librequest.so
tensorrtserver-1.11.0.data/purelib/tensorrtserver/api/model_config_pb2.py
tensorrtserver-1.11.0.data/purelib/tensorrtserver/api/request_status_pb2.py
tensorrtserver-1.11.0.data/purelib/tensorrtserver/api/server_status_pb2.py
tensorrtserver-1.11.0.data/purelib/tensorrtserver/cuda_shared_memory/__init__.py
tensorrtserver-1.11.0.data/purelib/tensorrtserver/cuda_shared_memory/libccudashm.so
tensorrtserver-1.11.0.data/purelib/tensorrtserver/shared_memory/__init__.py
tensorrtserver-1.11.0.data/purelib/tensorrtserver/shared_memory/libcshm.so
tensorrtserver-1.11.0.dist-info/METADATA
tensorrtserver-1.11.0.dist-info/WHEEL
tensorrtserver-1.11.0.dist-info/top_level.txt
tensorrtserver-1.11.0.dist-info/RECORD
